wasp_gateway/__init__.py
wasp_gateway/__main__.py
wasp_gateway/core.py
wasp_gateway/http/__init__.py
wasp_gateway/http/dispatcher.py
wasp_gateway/http/resolver.py
wasp_gateway-0.0.1.dist-info/DESCRIPTION.rst
wasp_gateway-0.0.1.dist-info/METADATA
wasp_gateway-0.0.1.dist-info/RECORD
wasp_gateway-0.0.1.dist-info/WHEEL
wasp_gateway-0.0.1.dist-info/metadata.json
wasp_gateway-0.0.1.dist-info/top_level.txt
